school/__init__.py
school/school_data.py
school_data-0.0.6.dist-info/METADATA
school_data-0.0.6.dist-info/WHEEL
school_data-0.0.6.dist-info/top_level.txt
school_data-0.0.6.dist-info/RECORD
