Metadata-Version: 2.1
Name: school-data
Version: 0.0.6
Summary: 나이스 학교 데이터 라이브러리
Home-page: https://github.com/cord0318/python_school_data
Author: Jung Ji-Hyo
Author-email: cord0318@gmail.com
License: GPL-V3
Keywords: korea,school,school_data,SchoolInfo,학교데이터
Platform: UNKNOWN
Classifier: Programming Language :: Python :: 3.8
Classifier: License :: OSI Approved :: GNU General Public License v3 (GPLv3)
Classifier: Development Status :: 5 - Production/Stable
Requires-Python: >=3
Requires-Dist: asyncio
Requires-Dist: aiohttp
Requires-Dist: pyjwt
